odoo9_addon_hr_holiday_notify_employee_manager-9.0.1.0.0.99.dev3-py2.7-nspkg.pth
odoo9_addon_hr_holiday_notify_employee_manager-9.0.1.0.0.99.dev3.dist-info/METADATA
odoo9_addon_hr_holiday_notify_employee_manager-9.0.1.0.0.99.dev3.dist-info/RECORD
odoo9_addon_hr_holiday_notify_employee_manager-9.0.1.0.0.99.dev3.dist-info/WHEEL
odoo9_addon_hr_holiday_notify_employee_manager-9.0.1.0.0.99.dev3.dist-info/namespace_packages.txt
odoo9_addon_hr_holiday_notify_employee_manager-9.0.1.0.0.99.dev3.dist-info/top_level.txt
odoo_addons/hr_holiday_notify_employee_manager/README.rst
odoo_addons/hr_holiday_notify_employee_manager/__init__.py
odoo_addons/hr_holiday_notify_employee_manager/__openerp__.py
odoo_addons/hr_holiday_notify_employee_manager/i18n/de.po
odoo_addons/hr_holiday_notify_employee_manager/i18n/es.po
odoo_addons/hr_holiday_notify_employee_manager/i18n/fi.po
odoo_addons/hr_holiday_notify_employee_manager/i18n/fr.po
odoo_addons/hr_holiday_notify_employee_manager/i18n/fr_CH.po
odoo_addons/hr_holiday_notify_employee_manager/i18n/hr_holiday_notify_employee_manager.pot
odoo_addons/hr_holiday_notify_employee_manager/i18n/it.po
odoo_addons/hr_holiday_notify_employee_manager/i18n/pt_BR.po
odoo_addons/hr_holiday_notify_employee_manager/i18n/ro.po
odoo_addons/hr_holiday_notify_employee_manager/i18n/sl.po
odoo_addons/hr_holiday_notify_employee_manager/models/__init__.py
odoo_addons/hr_holiday_notify_employee_manager/models/hr_holidays.py
odoo_addons/hr_holiday_notify_employee_manager/models/res_company.py
odoo_addons/hr_holiday_notify_employee_manager/static/description/icon.png
odoo_addons/hr_holiday_notify_employee_manager/tests/__init__.py
odoo_addons/hr_holiday_notify_employee_manager/tests/test_hr_holiday_notify_employee_manager.py
odoo_addons/hr_holiday_notify_employee_manager/views/res_company_view.xml
